{
  "$schema": "http://json-schema.org/draft-04/schema#",
  "id": "https://api.maas.global/maas-backend/profile/profile-devices-put/request",
  "description": "Request schema for profile-active-plan-put",
  "type": "object",
  "properties": {
    "identityId": {
      "type": "string",
      "pattern": "^[aepsu]{2}\\-[0-9A-Z_a-z]{4}\\-[0-9]:[0-9a-f]{8}(\\-[0-9a-f]{4}){3}\\-[0-9a-f]{12}$"
    },
    "payload": {
      "type": "object",
      "properties": {
        "devicePushToken": {
          "description": "Push token - 32 chars in iOS, up to 255 in Android",
          "type": "string",
          "pattern": "^(?:[\\0-\\uD7FF\\uE000-\\uFFFF]|[\\uD800-\\uDBFF][\\uDC00-\\uDFFF]|[\\uD800-\\uDBFF](?![\\uDC00-\\uDFFF])|(?:[^\\uD800-\\uDBFF]|^)[\\uDC00-\\uDFFF]){32,255}$"
        },
        "deviceIdentifier": {
          "description": "Universally unique identifier, see https://en.wikipedia.org/wiki/Universally_unique_identifier",
          "type": "string",
          "pattern": "^[0-9A-Fa-f]{8}(\\-[0-9A-Fa-f]{4}){3}\\-[0-9A-Fa-f]{12}$"
        },
        "deviceType": {
          "type": "string",
          "enum": [
            "iOS",
            "Android"
          ]
        }
      },
      "required": [
        "devicePushToken",
        "deviceIdentifier",
        "deviceType"
      ],
      "additionalProperties": false
    },
    "headers": {
      "Accept": {
        "description": "SemVer versioning schemas for versioning our resources",
        "type": "string",
        "pattern": "\\bapplication\\/json; [\\t-\\r \\xA0\\u1680\\u2000-\\u200A\\u2028\\u2029\\u202F\\u205F\\u3000\\uFEFF]+version=((0|[1-9][0-9]*)\\.(0|[1-9][0-9]*)\\.(0|[1-9][0-9]*)(\\-[\\-0-9a-z]+(?:\\.[\\-0-9a-z]+)*)?(?:\\+[\\-0-9a-z]+(?:\\.[\\-0-9a-z]+)*)?)\\b"
      },
      "X-Whim-User-Agent": {
        "type": "string",
        "minLength": 1
      }
    }
  },
  "additionalProperties": false
}